pyrequisite/__init__.py
pyrequisite/_create_empty_dict.py
pyrequisite/_flexible_multilevel_mkdir.py
pyrequisite-0.0.0.dist-info/LICENSE
pyrequisite-0.0.0.dist-info/METADATA
pyrequisite-0.0.0.dist-info/WHEEL
pyrequisite-0.0.0.dist-info/top_level.txt
pyrequisite-0.0.0.dist-info/RECORD
